syft_proto/__init__.py
syft_proto/_version.py
syft_proto/proto.json
syft_proto/proto.py
syft_proto/execution/__init__.py
syft_proto/execution/v1/__init__.py
syft_proto/execution/v1/communication_action_pb2.py
syft_proto/execution/v1/computation_action_pb2.py
syft_proto/execution/v1/placeholder_id_pb2.py
syft_proto/execution/v1/placeholder_pb2.py
syft_proto/execution/v1/plan_pb2.py
syft_proto/execution/v1/protocol_pb2.py
syft_proto/execution/v1/role_pb2.py
syft_proto/execution/v1/state_pb2.py
syft_proto/execution/v1/state_tensor_pb2.py
syft_proto/execution/v1/storage_action_pb2.py
syft_proto/execution/v1/type_wrapper_pb2.py
syft_proto/frameworks/__init__.py
syft_proto/frameworks/crypten/__init__.py
syft_proto/frameworks/crypten/onnx_model_pb2.py
syft_proto/frameworks/torch/__init__.py
syft_proto/frameworks/torch/fl/__init__.py
syft_proto/frameworks/torch/fl/v1/__init__.py
syft_proto/frameworks/torch/fl/v1/dataset_pb2.py
syft_proto/frameworks/torch/tensors/__init__.py
syft_proto/frameworks/torch/tensors/interpreters/__init__.py
syft_proto/frameworks/torch/tensors/interpreters/v1/__init__.py
syft_proto/frameworks/torch/tensors/interpreters/v1/additive_shared_pb2.py
syft_proto/frameworks/torch/tensors/interpreters/v1/precision_pb2.py
syft_proto/frameworks/torch/tensors/interpreters/v1/replicated_shared_pb2.py
syft_proto/generic/__init__.py
syft_proto/generic/string_pb2.py
syft_proto/generic/pointers/__init__.py
syft_proto/generic/pointers/v1/__init__.py
syft_proto/generic/pointers/v1/object_pointer_pb2.py
syft_proto/generic/pointers/v1/pointer_dataset_pb2.py
syft_proto/generic/pointers/v1/pointer_plan_pb2.py
syft_proto/generic/pointers/v1/pointer_tensor_pb2.py
syft_proto/messaging/__init__.py
syft_proto/messaging/v1/__init__.py
syft_proto/messaging/v1/message_pb2.py
syft_proto/types/__init__.py
syft_proto/types/syft/__init__.py
syft_proto/types/syft/v1/__init__.py
syft_proto/types/syft/v1/arg_pb2.py
syft_proto/types/syft/v1/id_pb2.py
syft_proto-0.5.3.dist-info/LICENSE
syft_proto-0.5.3.dist-info/METADATA
syft_proto-0.5.3.dist-info/WHEEL
syft_proto-0.5.3.dist-info/top_level.txt
syft_proto-0.5.3.dist-info/RECORD
