Metadata-Version: 2.1
Name: syft-proto
Version: 0.5.3
Summary: PySyft protocol constants.
Home-page: https://github.com/OpenMined/syft-proto
Author: OpenMined
Author-email: contact@openmined.org
License: LICENSE
Keywords: deep,learning,artificial,intelligence,homomorphic,encryption
Platform: UNKNOWN
Classifier: Development Status :: 3 - Alpha
Requires-Dist: protobuf (>=3.12.2)
